README.rst
setup.py
stopit.py
stopit.egg-info/PKG-INFO
stopit.egg-info/SOURCES.txt
stopit.egg-info/dependency_links.txt
stopit.egg-info/not-zip-safe
stopit.egg-info/top_level.txt