Metadata-Version: 1.1
Name: stopit
Version: 1.0.0
Summary: Timeout control decorator and context manager, raise exception in another thread
Home-page: http://pypi.python.org/pypi/stopit
Author: Gilles Lenfant
Author-email: gilles.lenfant@gmail.com
License: GPLv3
Keywords: threads timeout
Platform: UNKNOWN
Classifier: Topic :: Utilities
Classifier: Programming Language :: Python
Classifier: Programming Language :: Python :: Implementation :: CPython
Classifier: Programming Language :: Python :: 2.6
Classifier: Programming Language :: Python :: 2.7
Classifier: Programming Language :: Python :: 3.3
Classifier: Operating System :: OS Independent
Classifier: License :: OSI Approved :: GNU General Public License v3 (GPLv3)
Classifier: Intended Audience :: Developers
Classifier: Development Status :: 5 - Production/Stable
